.gitignore
LICENSE
MANIFEST.in
README.md
README.rst
pypi_upload.bat
setup.py
GISPython/AGServerHelper.py
GISPython/AGServerHelperNTLM.py
GISPython/AGServerHelperToken.py
GISPython/CachingHelper.py
GISPython/FTPHleper.py
GISPython/GDBHelper.py
GISPython/GDPSyncroniserHelper.py
GISPython/GDPSyncroniserHelper2.py
GISPython/GISPythonModule.py
GISPython/GISPythonTool.py
GISPython/GISPythonToolBase.py
GISPython/JsonParamsHelper.py
GISPython/MXDHelper.py
GISPython/MailHelper.py
GISPython/MyError.py
GISPython/PublisherHealper.py
GISPython/RarHelper.py
GISPython/SFTPHelper.py
GISPython/SimpleFileOps.py
GISPython/SimpleFileOpsSafe.py
GISPython/SysGISTools.py
GISPython/SysGISToolsSysParams.py
GISPython/SysTools_unittest.py
GISPython/TimerHelper.py
GISPython/ZipHelper.py
GISPython/__init__.py
GISPython/xmlParamsHealper.py
GISPython.egg-info/PKG-INFO
GISPython.egg-info/SOURCES.txt
GISPython.egg-info/dependency_links.txt
GISPython.egg-info/requires.txt
GISPython.egg-info/top_level.txt
GISPython/PShell/BackupOldFiles.ps1
GISPython/PShell/ClearDir.ps1
GISPython/PShell/GetLog.ps1