Metadata-Version: 1.1
Name: GISPython
Version: 60.3
Summary: Additional tools for administering and automating different ArcPy and ArcGIS Server geoprocessing operations. Package is intended for use with ArcGIS 10.2.1 and later (has been tested on ArcGIS 10.3.1, ArcGIS 10.4, ArcGIS 10.5, ArcGIS 10.6.1)
Home-page: https://github.com/lvmgeo/GISPython
Author: LVM GEO
Author-email: lvmGEOGit@lvm.lv
License: GPLv3
Keywords: ArcGIS,ArcPy,ArcGIS Server,automation
Platform: UNKNOWN
Classifier: Development Status :: 5 - Production/Stable
Classifier: Intended Audience :: Developers
Classifier: Intended Audience :: System Administrators
Classifier: Topic :: Scientific/Engineering :: GIS
Classifier: Topic :: Software Development :: Libraries :: Python Modules
Classifier: License :: OSI Approved :: GNU General Public License v3 (GPLv3)
Classifier: Operating System :: Microsoft :: Windows
Classifier: Programming Language :: Python
Classifier: Programming Language :: Python :: 2
Classifier: Programming Language :: Python :: 2.6
Classifier: Programming Language :: Python :: 2.7
